{
  "productList": [
    {
      "productName": "Livro 1",
      "autor": "Autor 1",
      "data": "2022-03-01T03:00:00.000Z",
      "id": 1
    },
    {
      "productName": "Livro 2 ",
      "autor": "Autor 2",
      "data": "2022-03-02T03:00:00.000Z",
      "id": 2
    },
    {
      "productName": "Livro 3 ",
      "autor": "Autor 2",
      "data": "2022-03-02T03:00:00.000Z",
      "id": 3
    },
    {
      "productName": "Livro 4",
      "autor": "Autor 2",
      "data": "2022-03-02T03:00:00.000Z",
      "id": 4
    },
    {
      "productName": "Livro 5",
      "autor": "Autor 5",
      "data": "2022-03-05T03:00:00.000Z",
      "id": 5
    }
  ],
  "signupUsers": [
    {
      "id": 1,
      "body": "some comment",
      "postId": 1
    },
    {
      "fullname": "Mayron Martins",
      "email": "mayronmartinscosta@hotmail.com",
      "password": "123456",
      "id": 2
    },
    {
      "fullname": "Jao da silva",
      "email": "jaosilva@gmail.com",
      "password": "1234",
      "id": 3
    },
    {
      "fullname": "Mayron Martins",
      "email": "mayronmartinscosta@hotmail.com",
      "password": "12345",
      "id": 4
    },
    {
      "fullname": "aaaa",
      "email": "aaaaa",
      "password": "123",
      "id": 5
    },
    {
      "fullname": "mayron",
      "email": "mayron@hotmail.com",
      "password": "12345",
      "id": 6
    },
    {
      "fullname": "Zeca Mantoja",
      "email": "zeca@gmail.com",
      "password": "1234",
      "id": 7
    }
  ],
  "admin": {
    "email": "admin",
    "password": "admin",
    "id": 1
  }
}